{
    "directed": false,
    "multigraph": false,
    "graph": {},
    "nodes": [
        {
            "basekV": 7.2,
            "latitude": 46.68246466,
            "longitude": -119.1114689,
            "id": "l3160871"
        },
        {
            "basekV": 7.2,
            "latitude": 46.6823162,
            "longitude": -119.1115866,
            "id": "p829975"
        },
        {
            "basekV": 7.2,
            "latitude": 46.68220684,
            "longitude": -119.1109185,
            "id": "p829974"
        },
        {
            "basekV": 7.2,
            "latitude": 46.68226664,
            "longitude": -119.1109343,
            "id": "m1149236"
        },
        {
            "basekV": 7.2,
            "latitude": 46.68236204,
            "longitude": -119.1091086,
            "id": "m1166377"
        },
        {
            "basekV": 7.2,
            "latitude": 46.68128346,
            "longitude": -119.1106745,
            "id": "l2805034"
        },
        {
            "basekV": 7.2,
            "latitude": 46.6822215,
            "longitude": -119.1119625,
            "id": "d5563942-4_int"
        },
        {
            "basekV": 7.2,
            "latitude": 46.68233676,
            "longitude": -119.1096861,
            "id": "m1166376"
        },
        {
            "basekV": 7.2,
            "latitude": 46.6823701,
            "longitude": -119.1089321,
            "id": "e184626"
        },
        {
            "basekV": 7.2,
            "latitude": 46.68233284,
            "longitude": -119.1097759,
            "id": "l2842384"
        },
        {
            "basekV": 7.2,
            "latitude": 46.68224172,
            "longitude": -119.1116456,
            "id": "m1149235"
        },
        {
            "basekV": 7.2,
            "latitude": 46.68370602,
            "longitude": -119.1118364,
            "id": "l3030203"
        },
        {
            "basekV": 7.2,
            "latitude": 46.68445132,
            "longitude": -119.1120871,
            "id": "l3179673"
        }
    ],
    "links": [
        {
            "name": "ln5957495-1",
            "element": "line",
            "length_unit": 3,
            "z_matrix_real": "[[0.0, 0.0, 0.0], [0.0, 0.0, 0.0], [0.0, 0.0, 1.6746561983883672]]",
            "z_matrix_imag": "[[0.0, 0.0, 0.0], [0.0, 0.0, 0.0], [0.0, 0.0, 0.9345603406595093]]",
            "length": 0.089472099,
            "num_phases": 1,
            "phases": "{'c'}",
            "is_switch": false,
            "is_open": false,
            "source": "l3160871",
            "target": "l3030203"
        },
        {
            "name": "ln6352834-1",
            "element": "line",
            "length_unit": 3,
            "z_matrix_real": "[[0.0, 0.0, 0.0], [0.0, 0.0, 0.0], [0.0, 0.0, 1.6746561983883674]]",
            "z_matrix_imag": "[[0.0, 0.0, 0.0], [0.0, 0.0, 0.0], [0.0, 0.0, 0.9345603406595093]]",
            "length": 0.012453696,
            "num_phases": 1,
            "phases": "{'c'}",
            "is_switch": false,
            "is_open": false,
            "source": "l3160871",
            "target": "p829975"
        },
        {
            "name": "ln5989329-1",
            "element": "line",
            "length_unit": 3,
            "z_matrix_real": "[[0.0, 0.0, 0.0], [0.0, 0.0, 0.0], [0.0, 0.0, 1.6746561983883672]]",
            "z_matrix_imag": "[[0.0, 0.0, 0.0], [0.0, 0.0, 0.0], [0.0, 0.0, 0.9345603406595093]]",
            "length": 0.00624901,
            "num_phases": 1,
            "phases": "{'c'}",
            "is_switch": false,
            "is_open": false,
            "source": "p829975",
            "target": "m1149235"
        },
        {
            "name": "ln6232159-1",
            "element": "line",
            "length_unit": 3,
            "z_matrix_real": "[[1.674656198388367, 0.0, 0.0], [0.0, 0.0, 0.0], [0.0, 0.0, 0.0]]",
            "z_matrix_imag": "[[0.9345603406595093, 0.0, 0.0], [0.0, 0.0, 0.0], [0.0, 0.0, 0.0]]",
            "length": 0.004284117,
            "num_phases": 1,
            "phases": "{'a'}",
            "is_switch": false,
            "is_open": false,
            "source": "p829974",
            "target": "m1149236"
        },
        {
            "name": "ln5989328-1",
            "element": "line",
            "length_unit": 3,
            "z_matrix_real": "[[1.6746561983883672, 0.0, 0.0], [0.0, 0.0, 0.0], [0.0, 0.0, 0.0]]",
            "z_matrix_imag": "[[0.9345603406595093, 0.0, 0.0], [0.0, 0.0, 0.0], [0.0, 0.0, 0.0]]",
            "length": 0.066163666,
            "num_phases": 1,
            "phases": "{'a'}",
            "is_switch": false,
            "is_open": false,
            "source": "p829974",
            "target": "l2805034"
        },
        {
            "name": "ln5805762-1",
            "element": "line",
            "length_unit": 3,
            "z_matrix_real": "[[0.27001903752089, 0.10995066546782975, 0.1135384900446312], [0.10995066546782975, 0.26463373510779326, 0.11074699310270608], [0.1135384900446312, 0.11074699310270608, 0.2716982793872438]]",
            "z_matrix_imag": "[[0.6959739725759836, 0.3335097859867847, 0.3082706578745229], [0.3335097859867847, 0.7087291002604085, 0.3502585204185219], [0.3082706578745229, 0.3502585204185219, 0.6920213416170082]]",
            "length": 0.067772686,
            "num_phases": 3,
            "phases": "{'a', 'b', 'c'}",
            "is_switch": false,
            "is_open": false,
            "source": "m1149236",
            "target": "l2842384"
        },
        {
            "name": "ln6018336-1",
            "element": "line",
            "length_unit": 3,
            "z_matrix_real": "[[0.27001903752089, 0.10995066546782975, 0.11353849004463118], [0.10995066546782975, 0.26463373510779326, 0.11074699310270608], [0.11353849004463118, 0.11074699310270608, 0.27169827938724384]]",
            "z_matrix_imag": "[[0.6959739725759836, 0.3335097859867847, 0.3082706578745229], [0.3335097859867847, 0.7087291002604085, 0.3502585204185219], [0.3082706578745229, 0.3502585204185219, 0.6920213416170082]]",
            "length": 0.041559119,
            "num_phases": 3,
            "phases": "{'a', 'b', 'c'}",
            "is_switch": false,
            "is_open": false,
            "source": "m1149236",
            "target": "m1149235"
        },
        {
            "name": "ln6326450-1",
            "element": "line",
            "length_unit": 3,
            "z_matrix_real": "[[0.27001903752089, 0.10995066546782975, 0.11353849004463121], [0.10995066546782975, 0.26463373510779326, 0.1107469931027061], [0.11353849004463121, 0.1107469931027061, 0.27169827938724384]]",
            "z_matrix_imag": "[[0.6959739725759836, 0.3335097859867847, 0.30827065787452285], [0.3335097859867847, 0.7087291002604086, 0.3502585204185219], [0.30827065787452285, 0.3502585204185219, 0.6920213416170082]]",
            "length": 0.010317742,
            "num_phases": 3,
            "phases": "{'a', 'b', 'c'}",
            "is_switch": false,
            "is_open": false,
            "source": "m1166377",
            "target": "e184626"
        },
        {
            "name": "ln5992960-1",
            "element": "line",
            "length_unit": 3,
            "z_matrix_real": "[[0.27001903752089, 0.10995066546782975, 0.1135384900446312], [0.10995066546782975, 0.26463373510779326, 0.1107469931027061], [0.1135384900446312, 0.1107469931027061, 0.27169827938724384]]",
            "z_matrix_imag": "[[0.6959739725759836, 0.3335097859867847, 0.3082706578745229], [0.3335097859867847, 0.7087291002604086, 0.35025852041852196], [0.3082706578745229, 0.35025852041852196, 0.6920213416170082]]",
            "length": 0.033759753,
            "num_phases": 3,
            "phases": "{'a', 'b', 'c'}",
            "is_switch": false,
            "is_open": false,
            "source": "m1166377",
            "target": "m1166376"
        },
        {
            "name": "ln5563942-4",
            "element": "line",
            "length_unit": 3,
            "z_matrix_real": "[[0.27001903752089, 0.10995066546782975, 0.1135384900446312], [0.10995066546782975, 0.2646337351077933, 0.11074699310270608], [0.1135384900446312, 0.11074699310270608, 0.2716982793872438]]",
            "z_matrix_imag": "[[0.6959739725759836, 0.3335097859867847, 0.30827065787452285], [0.3335097859867847, 0.7087291002604086, 0.35025852041852196], [0.30827065787452285, 0.35025852041852196, 0.6920213416170082]]",
            "length": 0.031133341,
            "num_phases": 3,
            "phases": "{'a', 'b', 'c'}",
            "is_switch": false,
            "is_open": false,
            "source": "d5563942-4_int",
            "target": "m1149235"
        },
        {
            "name": "ln5508630-1",
            "element": "line",
            "length_unit": 3,
            "z_matrix_real": "[[0.27001903752089, 0.10995066546782976, 0.11353849004463121], [0.10995066546782976, 0.26463373510779326, 0.1107469931027061], [0.11353849004463121, 0.1107469931027061, 0.2716982793872438]]",
            "z_matrix_imag": "[[0.6959739725759836, 0.3335097859867847, 0.3082706578745229], [0.3335097859867847, 0.7087291002604085, 0.35025852041852196], [0.3082706578745229, 0.35025852041852196, 0.6920213416170082]]",
            "length": 0.005246984,
            "num_phases": 3,
            "phases": "{'a', 'b', 'c'}",
            "is_switch": false,
            "is_open": false,
            "source": "m1166376",
            "target": "l2842384"
        },
        {
            "name": "ln5957496-1",
            "element": "line",
            "length_unit": 3,
            "z_matrix_real": "[[0.0, 0.0, 0.0], [0.0, 0.0, 0.0], [0.0, 0.0, 1.6746561983883672]]",
            "z_matrix_imag": "[[0.0, 0.0, 0.0], [0.0, 0.0, 0.0], [0.0, 0.0, 0.9345603406595093]]",
            "length": 0.054166013,
            "num_phases": 1,
            "phases": "{'c'}",
            "is_switch": false,
            "is_open": false,
            "source": "l3030203",
            "target": "l3179673"
        }
    ]
}